ChenUtils/__init__.py
ChenUtils/test.py
ChenUtils/LatestValidProxies/BaseSpider.py
ChenUtils/LatestValidProxies/Failed_attempt_on_asyncio.py
ChenUtils/LatestValidProxies/Proxy.py
ChenUtils/LatestValidProxies/Spider.py
ChenUtils/LatestValidProxies/SpiderConfiger.py
ChenUtils/LatestValidProxies/Spiders.py
ChenUtils/LatestValidProxies/__init__.py
ChenUtils/LatestValidProxies/log.py
ChenUtils/LatestValidProxies/settings.py
ChenUtils/Maths/__init__.py
ChenUtils/Maths/flt2bin2ieee754_32.py
ChenUtils-0.1.1.dist-info/LICENSE
ChenUtils-0.1.1.dist-info/METADATA
ChenUtils-0.1.1.dist-info/WHEEL
ChenUtils-0.1.1.dist-info/top_level.txt
ChenUtils-0.1.1.dist-info/RECORD
