Metadata-Version: 2.1
Name: ChenUtils
Version: 0.1.1
Summary: A package used to store various modules written by individuals.
Home-page: https://gitee.com/CodexploRe
Author: CodexploRe
Author-email: 1259864733@qq.com
License: MIT License
Classifier: Development Status :: 5 - Production/Stable
Classifier: Programming Language :: Python
Classifier: Programming Language :: Python :: 3.8
Classifier: Programming Language :: Python :: 3.9
Classifier: Programming Language :: Python :: 3.10
Classifier: Programming Language :: Python :: 3.11
Classifier: Programming Language :: Python :: 3.12
Classifier: License :: OSI Approved :: MIT License
Classifier: Operating System :: OS Independent
Classifier: Topic :: Software Development :: Libraries :: Python Modules
Requires-Python: >=3.8
License-File: LICENSE
Requires-Dist: aiohttp (>=3.8.5)
Requires-Dist: fake-useragent (>=1.2.1)
Requires-Dist: lxml (>=4.9.3)
Requires-Dist: Requests (>=2.31.0)
Requires-Dist: setuptools (>=68.1.2)
